cli.py
main.py
config/__init__.py
config/config.json
config/payloads.py
extras/__init__.py
extras/utils.py
scanners/__init__.py
scanners/httpscan.py
scanners/js_vuln_scan.py
scanners/lfi_scan.py
scanners/sqli_scan.py
scanners/ssti_scan.py
scanners/xss_scan.py
web_vulnscanner-0.1.4.dist-info/METADATA
web_vulnscanner-0.1.4.dist-info/WHEEL
web_vulnscanner-0.1.4.dist-info/entry_points.txt
web_vulnscanner-0.1.4.dist-info/top_level.txt
web_vulnscanner-0.1.4.dist-info/RECORD
