Metadata-Version: 2.4
Name: Web_Vulnscanner
Version: 0.1.4
Summary: A Simple CLI python tool to scan a website for common vulns.
Home-page: https://github.com/randomguy6407/Vulnscanner
Author: Randomguy
Author-email: gawzenneth@gmail.com
Requires-Python: >=3.7
Requires-Dist: playwright>=1.42.0
Requires-Dist: httpx>=0.27.0
Requires-Dist: requests>=2.31.0
Requires-Dist: h2>=4.1.0
Requires-Dist: rich>=13.0.0
Dynamic: author
Dynamic: author-email
Dynamic: description
Dynamic: description-content-type
Dynamic: home-page
Dynamic: requires-dist
Dynamic: requires-python
Dynamic: summary
